{
  "name": "bp_interface_remove_smoke",
  "description": "List-only smoke for removing an interface from a Blueprint. The edit call requires pre-staged Blueprint assets and is not executed in CI.",
  "category": "happy_path",
  "expectToolListed": true,
  "executeTool": false,
  "expectToolCallError": false,
  "request": {
    "jsonrpc": "2.0",
    "id": 141,
    "method": "tools/call",
    "params": {
      "name": "unreal.bp_interface_remove",
      "arguments": {
        "blueprintPath": "/Game/__UEvolveMcpTest_chunk2b/BP_RefactorSmoke",
        "interfacePath": "/Game/__UEvolveMcpTest_chunk2b/BPI_RefactorSmoke.BPI_RefactorSmoke_C",
        "preserveFunctions": false
      }
    }
  }
}
